Metadata-Version: 2.1
Name: cncdev7
Version: 0.1
Summary: Salom matnini 100 marta chiqaruvchi kutubxona
Home-page: https://github.com/cncdev7/cncdev7
Author: cncdev7
